dittohunt/LICENSE.txt
dittohunt/__init__.py
dittohunt/__main__.py
dittohunt/dittohunt.py
dittohunt/dittohunt.ui
dittohunt/dittohunt_rc.py
dittohunt/finddups.py
dittohunt/pyside_dynamic.py
dittohunt/qt.py
dittohunt/version.py
dittohunt/res/dittohunt.ico
dittohunt/res/dittohunt.qrc
dittohunt/res/32x32/dittohunt.png
dittohunt-1.1.dist-info/DESCRIPTION.rst
dittohunt-1.1.dist-info/METADATA
dittohunt-1.1.dist-info/RECORD
dittohunt-1.1.dist-info/WHEEL
dittohunt-1.1.dist-info/entry_points.txt
dittohunt-1.1.dist-info/metadata.json
dittohunt-1.1.dist-info/top_level.txt
