Metadata-Version: 2.0
Name: dittohunt
Version: 1.1
Summary: A duplicate file finder, previewer, and deleter.
Home-page: https://github.com/digitalpeer/dittohunt
Author: Joshua Henderson
Author-email: digitalpeer@digitalpeer.com
License: UNKNOWN
Download-URL: https://github.com/digitalpeer/dittohunt/zipball/master
Keywords: file find duplicate
Platform: UNKNOWN
Classifier: Development Status :: 3 - Alpha
Classifier: Environment :: X11 Applications :: Qt
Classifier: Natural Language :: English
Classifier: Operating System :: OS Independent
Classifier: Programming Language :: Python :: 2
Classifier: Programming Language :: Python :: 2.7
Classifier: Programming Language :: Python :: 3
Classifier: Programming Language :: Python :: 3.5
Classifier: License :: OSI Approved :: GNU General Public License v3 (GPLv3)
Classifier: Topic :: Desktop Environment :: File Managers
Classifier: Topic :: System :: Filesystems
Classifier: Topic :: Utilities
Classifier: Intended Audience :: End Users/Desktop
Classifier: Intended Audience :: Information Technology
Classifier: Intended Audience :: Science/Research
